{"cameraMode":{"drawMode":0,"name":"Shaded","section":"Shading Mode"},"sceneLighting":true,"audioPlay":false,"sceneViewState":{"showFog":true,"showMaterialUpdate":false,"showSkybox":true,"showFlares":true,"showImageEffects":true,"showParticleSystems":true},"in2DMode":false,"pivot":{"x":15.708500862121582,"y":-2.4907965660095217,"z":2.3063607215881349},"rotation":{"x":-0.22518640756607057,"y":0.5906263589859009,"z":-0.1762479543685913,"w":-0.7546080350875855},"size":6.681386947631836,"orthographic":false}